LICENSE.txt
MANIFEST.in
NEWS.txt
README.txt
setup.py
src/bp/__init__.py
src/bp.rename.egg-info/PKG-INFO
src/bp.rename.egg-info/SOURCES.txt
src/bp.rename.egg-info/dependency_links.txt
src/bp.rename.egg-info/entry_points.txt
src/bp.rename.egg-info/namespace_packages.txt
src/bp.rename.egg-info/not-zip-safe
src/bp.rename.egg-info/requires.txt
src/bp.rename.egg-info/top_level.txt
src/bp/rename/__init__.py
src/bp/rename/table.py
src/bp/rename/terminal.py