Metadata-Version: 1.0
Name: bp.rename
Version: 0.1.1
Summary: Command line script to make common file renaming operations easier
Home-page: http://github.com/disko/bp.rename
Author: Andreas Kaiser
Author-email: disko@binary-punks.com
License: BSD
Keywords: command line filesystem
Platform: UNKNOWN
Classifier: Development Status :: 2 - Pre-Alpha
Classifier: Programming Language :: Python
Classifier: Environment :: Console
Classifier: Intended Audience :: End Users/Desktop
Classifier: Intended Audience :: System Administrators
Classifier: License :: OSI Approved :: BSD License
Classifier: Operating System :: POSIX
Classifier: Topic :: Utilities
